[
  { "id": "q001", "theme": "calm", "text": "Природа никогда не спешит, но всё совершается.", "author": "Лао-цзы" },
  { "id": "q002", "theme": "calm", "text": "Мир приходит изнутри. Не ищи его снаружи.", "author": "Будда" },
  { "id": "q003", "theme": "calm", "text": "Тишина — язык Бога, всё остальное — плохой перевод.", "author": "Руми" },
  { "id": "q004", "theme": "calm", "text": "Осознай глубоко: настоящий момент — это всё, что у тебя есть.", "author": "Экхарт Толле" },
  { "id": "q005", "theme": "calm", "text": "Все беды человека оттого, что он не умеет спокойно сидеть в комнате.", "author": "Блез Паскаль" },
  { "id": "q006", "theme": "calm", "text": "Не позволяй поведению других разрушить твой внутренний покой.", "author": "Далай-лама XIV" },
  { "id": "q007", "theme": "calm", "text": "Дай мне спокойствие принять то, что я не могу изменить.", "author": "Рейнгольд Нибур" },
  { "id": "q008", "theme": "calm", "text": "Где бы ты ни был — будь там целиком.", "author": "Экхарт Толле" },
  { "id": "q009", "theme": "calm", "text": "Жизнь — это баланс между тем, чтобы держаться и отпускать.", "author": "Руми" },
  { "id": "q010", "theme": "calm", "text": "Внутри тебя есть тишина и убежище, куда можно вернуться в любой момент.", "author": "Герман Гессе" },
  { "id": "q011", "theme": "calm", "text": "Спокойный ум приносит внутреннюю силу и уверенность в себе.", "author": "Далай-лама XIV" },
  { "id": "q012", "theme": "calm", "text": "Лучшее оружие против стресса — способность выбрать одну мысль вместо другой.", "author": "Уильям Джеймс" },
  { "id": "q013", "theme": "calm", "text": "Не дай вчерашнему дню забрать слишком много у сегодняшнего.", "author": "Уилл Роджерс" },
  { "id": "q014", "theme": "calm", "text": "Улыбка — источник радости, но иногда радость — источник улыбки.", "author": "Тит Нат Хан" },
  { "id": "q015", "theme": "calm", "text": "Поле, которое отдохнуло, даёт обильный урожай.", "author": "Овидий" },
  { "id": "q016", "theme": "calm", "text": "Когда я отпускаю то, кем являюсь, я становлюсь тем, кем могу быть.", "author": "Лао-цзы" },
  { "id": "q017", "theme": "calm", "text": "Между стимулом и реакцией есть пространство. В этом пространстве — наша свобода.", "author": "Виктор Франкл" },
  { "id": "q018", "theme": "calm", "text": "Капля точит камень не силой, а частотой падения.", "author": "Овидий" },
  { "id": "q019", "theme": "calm", "text": "Кто живёт в гармонии с собой, живёт в гармонии со вселенной.", "author": "Марк Аврелий" },
  { "id": "q020", "theme": "calm", "text": "Покой начинается с улыбки.", "author": "Мать Тереза" },
  { "id": "q021", "theme": "calm", "text": "Счастье не в том, чтобы делать всегда, что хочешь, а в том, чтобы хотеть того, что делаешь.", "author": "Лев Толстой" },
  { "id": "q022", "theme": "calm", "text": "Вода, что течёт мягко, со временем побеждает камень.", "author": "Лао-цзы" },
  { "id": "q023", "theme": "calm", "text": "Самый сильный тот, кто владеет собой.", "author": "Сенека" },
  { "id": "q024", "theme": "calm", "text": "Дыши. Замечай этот момент — он уже достаточно полон.", "author": "Тит Нат Хан" },
  { "id": "q025", "theme": "calm", "text": "Спокойствие ума — это драгоценность мудрости.", "author": "Джеймс Аллен" },

  { "id": "q026", "theme": "focus", "text": "Куда направлено внимание, туда течёт энергия.", "author": "Тони Роббинс" },
  { "id": "q027", "theme": "focus", "text": "Сосредоточь все мысли на текущем деле: лучи солнца не жгут, пока их не собрать в фокус.", "author": "Александр Белл" },
  { "id": "q028", "theme": "focus", "text": "Успешный воин — это обычный человек с фокусом, острым как лазер.", "author": "Брюс Ли" },
  { "id": "q029", "theme": "focus", "text": "Недостаточно быть занятым. Вопрос в том, чем именно ты занят.", "author": "Генри Дэвид Торо" },
  { "id": "q030", "theme": "focus", "text": "Простота — высшая степень утончённости.", "author": "Леонардо да Винчи" },
  { "id": "q031", "theme": "focus", "text": "Фокус — это умение говорить «нет».", "author": "Стив Джобс" },
  { "id": "q032", "theme": "focus", "text": "Остерегайся пустоты занятой жизни.", "author": "Сократ" },
  { "id": "q033", "theme": "focus", "text": "Главное — чтобы главное оставалось главным.", "author": "Стивен Кови" },
  { "id": "q034", "theme": "focus", "text": "Кто гонится за двумя зайцами, не поймает ни одного.", "author": "Конфуций" },
  { "id": "q035", "theme": "focus", "text": "Делай одно дело за раз и вкладывай в него всю душу.", "author": "Свами Вивекананда" },
  { "id": "q036", "theme": "focus", "text": "Проблема не в нехватке времени, а в отсутствии направления.", "author": "Зиг Зиглар" },
  { "id": "q037", "theme": "focus", "text": "Ты можешь сделать что угодно, но не всё сразу.", "author": "Дэвид Аллен" },
  { "id": "q038", "theme": "focus", "text": "Действие — основополагающий ключ к любому успеху.", "author": "Пабло Пикассо" },
  { "id": "q039", "theme": "focus", "text": "Мы то, что постоянно делаем. Совершенство — не действие, а привычка.", "author": "Аристотель" },
  { "id": "q040", "theme": "focus", "text": "Либо ты управляешь днём, либо день управляет тобой.", "author": "Джим Рон" },
  { "id": "q041", "theme": "focus", "text": "Самый короткий способ сделать многое — делать по одному делу за раз.", "author": "В. А. Моцарт" },
  { "id": "q042", "theme": "focus", "text": "Фокус — это решение о том, чего ты делать не будешь.", "author": "Джон Кармак" },
  { "id": "q043", "theme": "focus", "text": "Делать два дела сразу — значит не делать ни одного.", "author": "Публилий Сир" },
  { "id": "q044", "theme": "focus", "text": "Ум нужен, чтобы рождать идеи, а не хранить их.", "author": "Дэвид Аллен" },
  { "id": "q045", "theme": "focus", "text": "То, на чём ты держишь фокус, растёт.", "author": "Рой Беннетт" },
  { "id": "q046", "theme": "focus", "text": "Концентрация — секрет силы.", "author": "Ральф Уолдо Эмерсон" },
  { "id": "q047", "theme": "focus", "text": "Искусство быть мудрым — знать, что можно не замечать.", "author": "Уильям Джеймс" },
  { "id": "q048", "theme": "focus", "text": "Впитывай полезное, отбрасывай бесполезное, добавляй своё.", "author": "Брюс Ли" },
  { "id": "q049", "theme": "focus", "text": "Мы редко достигаем желаемого, потому что не концентрируем внимание.", "author": "Тони Роббинс" },
  { "id": "q050", "theme": "focus", "text": "Кто хочет сдвинуть мир, пусть сначала сдвинет себя.", "author": "Сократ" },

  { "id": "q051", "theme": "motivation", "text": "Чтобы начать, перестань говорить и начни делать.", "author": "Уолт Дисней" },
  { "id": "q052", "theme": "motivation", "text": "Успех не окончателен, поражение не смертельно: значение имеет смелость продолжать.", "author": "Уинстон Черчилль" },
  { "id": "q053", "theme": "motivation", "text": "Поверь, что можешь, — и ты уже на полпути.", "author": "Теодор Рузвельт" },
  { "id": "q054", "theme": "motivation", "text": "Всё кажется невозможным, пока не будет сделано.", "author": "Нельсон Мандела" },
  { "id": "q055", "theme": "motivation", "text": "Считаешь ли ты, что можешь, или что не можешь, — ты прав в обоих случаях.", "author": "Генри Форд" },
  { "id": "q056", "theme": "motivation", "text": "Будущее принадлежит тем, кто верит в красоту своей мечты.", "author": "Элеонора Рузвельт" },
  { "id": "q057", "theme": "motivation", "text": "Не смотри на часы; делай то же, что и они, — продолжай идти.", "author": "Сэм Левенсон" },
  { "id": "q058", "theme": "motivation", "text": "Единственный способ делать великое дело — любить то, что делаешь.", "author": "Стив Джобс" },
  { "id": "q059", "theme": "motivation", "text": "Наша слава не в том, чтобы никогда не падать, а в том, чтобы подниматься каждый раз.", "author": "Конфуций" },
  { "id": "q060", "theme": "motivation", "text": "Упади семь раз — поднимись восемь.", "author": "Японская пословица" },
  { "id": "q061", "theme": "motivation", "text": "Всё, чего ты когда-либо хотел, находится по ту сторону страха.", "author": "Джордж Аддэр" },
  { "id": "q062", "theme": "motivation", "text": "Через год ты пожалеешь, что не начал сегодня.", "author": "Карен Лэмб" },
  { "id": "q063", "theme": "motivation", "text": "Путь в тысячу ли начинается с одного шага.", "author": "Лао-цзы" },
  { "id": "q064", "theme": "motivation", "text": "Трудности часто готовят обычных людей к необычной судьбе.", "author": "К. С. Льюис" },
  { "id": "q065", "theme": "motivation", "text": "Неважно, как медленно ты идёшь, пока ты не останавливаешься.", "author": "Конфуций" },
  { "id": "q066", "theme": "motivation", "text": "Начни с того, что есть, там, где ты есть, и делай, что можешь.", "author": "Артур Эш" },
  { "id": "q067", "theme": "motivation", "text": "Удача благоволит подготовленному уму.", "author": "Луи Пастер" },
  { "id": "q068", "theme": "motivation", "text": "Ты промахиваешься в 100% бросков, которые не сделал.", "author": "Уэйн Гретцки" },
  { "id": "q069", "theme": "motivation", "text": "Если можешь мечтать об этом — можешь это сделать.", "author": "Уолт Дисней" },
  { "id": "q070", "theme": "motivation", "text": "Действуй так, будто твои поступки имеют значение. Так и есть.", "author": "Уильям Джеймс" },
  { "id": "q071", "theme": "motivation", "text": "Секрет того, чтобы вырваться вперёд, — просто начать.", "author": "Марк Твен" },
  { "id": "q072", "theme": "motivation", "text": "Энергия и упорство покоряют всё.", "author": "Бенджамин Франклин" },
  { "id": "q073", "theme": "motivation", "text": "Хорошо сделанное лучше хорошо сказанного.", "author": "Бенджамин Франклин" },
  { "id": "q074", "theme": "motivation", "text": "Упорство — это не один долгий забег, а много коротких один за другим.", "author": "Уолтер Эллиот" },
  { "id": "q075", "theme": "motivation", "text": "Лучшее время посадить дерево было 20 лет назад. Второе лучшее — сегодня.", "author": "Китайская пословица" },

  { "id": "q076", "theme": "stoicism", "text": "У тебя есть власть над своим умом, а не над внешними событиями. Осознай это — и обретёшь силу.", "author": "Марк Аврелий" },
  { "id": "q077", "theme": "stoicism", "text": "Мы чаще страдаем в воображении, чем в реальности.", "author": "Сенека" },
  { "id": "q078", "theme": "stoicism", "text": "Важно не то, что с тобой происходит, а то, как ты на это реагируешь.", "author": "Эпиктет" },
  { "id": "q079", "theme": "stoicism", "text": "Препятствие на пути становится самим путём.", "author": "Марк Аврелий" },
  { "id": "q080", "theme": "stoicism", "text": "Кто храбр, тот свободен.", "author": "Сенека" },
  { "id": "q081", "theme": "stoicism", "text": "Удача — это когда подготовка встречает возможность.", "author": "Сенека" },
  { "id": "q082", "theme": "stoicism", "text": "Богат не тот, у кого много, а тот, кому мало нужно.", "author": "Эпиктет" },
  { "id": "q083", "theme": "stoicism", "text": "Не трать время на споры о том, каким должен быть хороший человек. Будь им.", "author": "Марк Аврелий" },
  { "id": "q084", "theme": "stoicism", "text": "Счастье твоей жизни зависит от качества твоих мыслей.", "author": "Марк Аврелий" },
  { "id": "q085", "theme": "stoicism", "text": "Если это неправильно — не делай; если это неправда — не говори.", "author": "Марк Аврелий" },
  { "id": "q086", "theme": "stoicism", "text": "Не свободен тот, кто не владеет собой.", "author": "Эпиктет" },
  { "id": "q087", "theme": "stoicism", "text": "Трудности укрепляют ум, как труд укрепляет тело.", "author": "Сенека" },
  { "id": "q088", "theme": "stoicism", "text": "Сначала реши, кем хочешь быть, а потом делай то, что для этого нужно.", "author": "Эпиктет" },
  { "id": "q089", "theme": "stoicism", "text": "Каждое начало рождается из конца другого начала.", "author": "Сенека" },
  { "id": "q090", "theme": "stoicism", "text": "Пока мы откладываем жизнь, она проходит.", "author": "Сенека" },
  { "id": "q091", "theme": "stoicism", "text": "Начни жить сейчас и считай каждый день отдельной жизнью.", "author": "Сенека" },
  { "id": "q092", "theme": "stoicism", "text": "Человек покоряет мир, покоряя себя.", "author": "Зенон Китийский" },
  { "id": "q093", "theme": "stoicism", "text": "Сколько ещё ты будешь ждать, прежде чем потребуешь от себя лучшего?", "author": "Эпиктет" },
  { "id": "q094", "theme": "stoicism", "text": "Лучшая месть — не быть похожим на того, кто причинил зло.", "author": "Марк Аврелий" },
  { "id": "q095", "theme": "stoicism", "text": "Мы не выбираем обстоятельства, но всегда выбираем, как ответить на них.", "author": "Эпиктет" },
  { "id": "q096", "theme": "stoicism", "text": "Пока живёшь — учись жить.", "author": "Сенека" },
  { "id": "q097", "theme": "stoicism", "text": "Кто страдает раньше, чем нужно, страдает больше, чем нужно.", "author": "Сенека" },
  { "id": "q098", "theme": "stoicism", "text": "Камень не отполировать без трения, а человека не закалить без испытаний.", "author": "Сенека" },
  { "id": "q099", "theme": "stoicism", "text": "Окружай себя теми, кто делает тебя лучше.", "author": "Сенека" },
  { "id": "q100", "theme": "stoicism", "text": "Если хочешь развиваться, будь готов иногда показаться глупым.", "author": "Эпиктет" }
]
